<?xml version="1.0" encoding="UTF-8" ?>
<c cl="0">
    <d d1="101190801" d2="徐州" d3="xuzhou" d4="江苏"/>
    <d d1="101190101" d2="南京" d3="nanjing" d4="江苏"/>
    <d d1="101190401" d2="苏州" d3="suzhou" d4="江苏"/>
    <d d1="101191101" d2="常州" d3="changzhou" d4="江苏"/>
    <d d1="101190201" d2="无锡" d3="wuxi" d4="江苏"/>
    <d d1="101190501" d2="南通" d3="nantong" d4="江苏"/>
    <d d1="101190901" d2="淮安" d3="huaian" d4="江苏"/>
    <d d1="101191001" d2="连云港" d3="lianyungang" d4="江苏"/>
    <d d1="101190601" d2="扬州" d3="yangzhou" d4="江苏"/>
    <d d1="101191301" d2="宿迁" d3="suqian" d4="江苏"/>
    <d d1="101190701" d2="盐城" d3="yancheng" d4="江苏"/>
    <d d1="101191201" d2="泰州" d3="taizhou" d4="江苏"/>
    <d d1="101190301" d2="镇江" d3="zhenjiang" d4="江苏"/>

</c>